trainly/__init__.py
trainly/client.py
trainly/models.py
trainly/v1_client.py
trainly-0.1.0.dist-info/licenses/LICENSE
trainly-0.1.0.dist-info/METADATA
trainly-0.1.0.dist-info/WHEEL
trainly-0.1.0.dist-info/top_level.txt
trainly-0.1.0.dist-info/RECORD
