Metadata-Version: 2.4
Name: trainly
Version: 0.1.0
Summary: Dead simple RAG integration for Python applications
Author-email: Trainly Team <support@trainly.com>
License-Expression: MIT
Project-URL: Homepage, https://trainly.com
Project-URL: Documentation, https://trainly.com/docs/python-sdk
Project-URL: Repository, https://github.com/trainly/python-sdk
Project-URL: Bug Reports, https://github.com/trainly/python-sdk/issues
Keywords: trainly,rag,ai,llm,knowledge-base,embeddings,vector-search
Classifier: Development Status :: 4 - Beta
Classifier: Intended Audience :: Developers
Classifier: Programming Language :: Python :: 3
Classifier: Programming Language :: Python :: 3.8
Classifier: Programming Language :: Python :: 3.9
Classifier: Programming Language :: Python :: 3.10
Classifier: Programming Language :: Python :: 3.11
Classifier: Programming Language :: Python :: 3.12
Classifier: Topic :: Software Development :: Libraries :: Python Modules
Classifier: Topic :: Scientific/Engineering :: Artificial Intelligence
Requires-Python: >=3.8
License-File: LICENSE
Requires-Dist: requests>=2.25.0
Provides-Extra: dev
Requires-Dist: pytest>=7.0.0; extra == "dev"
Requires-Dist: pytest-cov>=4.0.0; extra == "dev"
Requires-Dist: black>=22.0.0; extra == "dev"
Requires-Dist: flake8>=5.0.0; extra == "dev"
Requires-Dist: mypy>=0.990; extra == "dev"
Requires-Dist: types-requests>=2.25.0; extra == "dev"
Dynamic: license-file
